honegumi_rag_assistant/__init__.py
honegumi_rag_assistant/__main__.py
honegumi_rag_assistant/app_config.py
honegumi_rag_assistant/build_vector_store.py
honegumi_rag_assistant/extractors.py
honegumi_rag_assistant/orchestrator.py
honegumi_rag_assistant/states.py
honegumi_rag_assistant/timing_utils.py
honegumi_rag_assistant/nodes/__init__.py
honegumi_rag_assistant/nodes/code_writer.py
honegumi_rag_assistant/nodes/parameter_selector.py
honegumi_rag_assistant/nodes/retrieval_planner.py
honegumi_rag_assistant/nodes/retriever.py
honegumi_rag_assistant/nodes/reviewer.py
honegumi_rag_assistant/nodes/skeleton_generator.py
honegumi_rag_assistant-0.1.7.dist-info/licenses/LICENSE.txt
honegumi_rag_assistant-0.1.7.dist-info/METADATA
honegumi_rag_assistant-0.1.7.dist-info/WHEEL
honegumi_rag_assistant-0.1.7.dist-info/entry_points.txt
honegumi_rag_assistant-0.1.7.dist-info/top_level.txt
honegumi_rag_assistant-0.1.7.dist-info/RECORD
