Metadata-Version: 2.4
Name: honegumi_rag_assistant
Version: 0.1.7
Summary: Agentic AI system for generating Bayesian optimization code from natural language using LangGraph and OpenAI GPT models
Home-page: https://github.com/hasan-sayeed/honegumi_rag_assistant
Author: Hasan Muhammad Sayeed
Author-email: hasan.sayeed.71.93@gmail.com
License: MIT
Project-URL: Documentation, https://github.com/hasan-sayeed/honegumi_rag_assistant
Project-URL: Source, https://github.com/hasan-sayeed/honegumi_rag_assistant
Project-URL: Tracker, https://github.com/hasan-sayeed/honegumi_rag_assistant/issues
Platform: any
Classifier: Development Status :: 4 - Beta
Classifier: Programming Language :: Python
Requires-Python: >=3.11
License-File: LICENSE.txt
Requires-Dist: openai==2.3.0
Requires-Dist: langchain-openai==0.3.35
Requires-Dist: honegumi==0.4.3
Requires-Dist: langchain==0.3.27
Requires-Dist: langchain-community==0.3.31
Requires-Dist: langgraph==0.6.10
Requires-Dist: faiss-cpu==1.12.0
Requires-Dist: python-dotenv
Requires-Dist: numpy==2.3.3
Requires-Dist: pandas==2.3.3
Provides-Extra: testing
Requires-Dist: setuptools; extra == "testing"
Requires-Dist: pytest; extra == "testing"
Requires-Dist: pytest-cov; extra == "testing"
Dynamic: license-file
